tweetrel/__init__.py
tweetrel/_nbdev.py
tweetrel/core.py
tweetrel-0.0.5.dist-info/LICENSE
tweetrel-0.0.5.dist-info/METADATA
tweetrel-0.0.5.dist-info/WHEEL
tweetrel-0.0.5.dist-info/entry_points.txt
tweetrel-0.0.5.dist-info/top_level.txt
tweetrel-0.0.5.dist-info/RECORD
