Metadata-Version: 2.1
Name: tweetrel
Version: 0.0.5
Summary: Use GitHub Actions to send a tweet when you make a new release
Home-page: https://github.com/fastai/tweetrel/tree/master/
Author: Jeremy Howard
Author-email: info@fast.ai
License: Apache Software License 2.0
Keywords: twitter release github api
Platform: UNKNOWN
Classifier: Development Status :: 3 - Alpha
Classifier: Intended Audience :: Developers
Classifier: License :: OSI Approved :: Apache Software License
Classifier: Natural Language :: English
Classifier: Programming Language :: Python :: 3.6
Classifier: Programming Language :: Python :: 3.7
Classifier: Programming Language :: Python :: 3.8
Requires-Python: >=3.6
Requires-Dist: tweepy
Requires-Dist: ghapi
